mathutils_vinit/__init__.py
mathutils_vinit/operations.py
mathutils_vinit/roots.py
mathutils_vinit/pretrained/best_model.t7
mathutils_vinit/pretrained/test.py
mathutils_vinit-0.0.7.dist-info/LICENSE
mathutils_vinit-0.0.7.dist-info/METADATA
mathutils_vinit-0.0.7.dist-info/WHEEL
mathutils_vinit-0.0.7.dist-info/top_level.txt
mathutils_vinit-0.0.7.dist-info/RECORD
