Metadata-Version: 2.1
Name: mathutils_vinit
Version: 0.0.7
Summary: A small example package
Author-email: vinit sarode <vinitsarode5@gmail.com>
Project-URL: Homepage, https://github.com/pypa/sampleproject
Project-URL: Issues, https://github.com/pypa/sampleproject/issues
Classifier: Programming Language :: Python :: 3
Classifier: License :: OSI Approved :: MIT License
Classifier: Operating System :: OS Independent
Requires-Python: >=3.8
License-File: LICENSE
Requires-Dist: pytest ==8.1.1
